tinytextgrad/__init__.py
tinytextgrad/llm.py
tinytextgrad/prompt.py
tinytextgrad/ttg.py
tinytextgrad/sys_prompts/apply_gradient.md
tinytextgrad/sys_prompts/cleanup_text.md
tinytextgrad/sys_prompts/prompt_loss.md
tinytextgrad-0.2.5.dist-info/METADATA
tinytextgrad-0.2.5.dist-info/WHEEL
tinytextgrad-0.2.5.dist-info/licenses/LICENSE
tinytextgrad-0.2.5.dist-info/RECORD
