Metadata-Version: 2.3
Name: tinytextgrad
Version: 0.2.5
Summary: Automatic prompt optimization by iteratively refining them using feedback
Project-URL: GitHub, https://github.com/witt3rd/tinytextgrad
Author-email: Donald Thompson <witt3rd@witt3rd.com>
License-File: LICENSE
Requires-Python: >=3.8
Requires-Dist: jinja2>=3.1.4
Requires-Dist: litellm>=1.41.15
Requires-Dist: loguru>=0.7.2
Requires-Dist: pydotenv>=0.0.7
Requires-Dist: pyyaml>=6.0.1
